README.rst
setup.py
spot_sdk/__init__.py
spot_sdk/tests.py
spot_sdk.egg-info/PKG-INFO
spot_sdk.egg-info/SOURCES.txt
spot_sdk.egg-info/dependency_links.txt
spot_sdk.egg-info/top_level.txt