Metadata-Version: 1.1
Name: spot-sdk
Version: 2018.2.22.1
Summary: SDK for the find me spot
Home-page: https://github.com/gregology/spot-sdk
Author: Greg Clarke
Author-email: greg@gho.st
License: MIT
Keywords: spot
Platform: UNKNOWN
Classifier: Development Status :: 4 - Beta
Classifier: Intended Audience :: Developers
Classifier: Topic :: Software Development :: Build Tools
Classifier: License :: OSI Approved :: MIT License
Classifier: Programming Language :: Python
